copypy/__init__.py
copypy/__main__.py
copypy/copypy.py
copypy-0.0.9.dist-info/LICENSE
copypy-0.0.9.dist-info/METADATA
copypy-0.0.9.dist-info/WHEEL
copypy-0.0.9.dist-info/top_level.txt
copypy-0.0.9.dist-info/RECORD
