Metadata-Version: 2.1
Name: copypy
Version: 0.0.9
Summary: Video Transcription
Author-email: Juan Rojas <jfernandorojasc@gmail.com>
Project-URL: Homepage, https://github.com/DevArKaDiA/transpy
Project-URL: Bug Tracker, https://github.com/DevArKaDiA/transpy
Classifier: Programming Language :: Python :: 3
Classifier: License :: OSI Approved :: MIT License
Classifier: Operating System :: OS Independent
Requires-Python: >=3.8
License-File: LICENSE
Requires-Dist: SpeechRecognition ==3.10.0
Requires-Dist: pydub ==0.25.1
Requires-Dist: numpy ==1.26.2
Requires-Dist: soundfile ==0.12.1
Requires-Dist: torch ==2.1.1
Requires-Dist: openai-whisper ==20231106
